django_split_input/__init__.py
django_split_input/apps.py
django_split_input/static/django_split_input/css/input.css
django_split_input/static/django_split_input/js/input.js
django_split_input/templates/django_split_input/widget.html
django_split_input/widgets.py
django_split_input-0.2.2.post1.dist-info/LICENSE
django_split_input-0.2.2.post1.dist-info/WHEEL
django_split_input-0.2.2.post1.dist-info/METADATA
django_split_input-0.2.2.post1.dist-info/RECORD
