Metadata-Version: 2.1
Name: django-split-input
Version: 0.2.2.post1
Summary: A widget to have a django text input split into multiple HTML inputs.
Home-page: https://edugit.org/AlekSIS/libs/django-split-input
License: Apache-2.0
Keywords: django,widget
Author: Julian Leucker
Author-email: leuckerj@gmail.com
Requires-Python: >=3.7,<4.0
Classifier: Environment :: Web Environment
Classifier: Framework :: Django :: 2.0
Classifier: Framework :: Django :: 2.1
Classifier: Framework :: Django :: 2.2
Classifier: Framework :: Django :: 3.0
Classifier: Framework :: Django :: 3.1
Classifier: Intended Audience :: Developers
Classifier: License :: OSI Approved :: Apache Software License
Classifier: Programming Language :: Python :: 3
Classifier: Programming Language :: Python :: 3.7
Classifier: Programming Language :: Python :: 3.8
Classifier: Programming Language :: Python :: 3.9
Classifier: Topic :: Internet :: WWW/HTTP :: WSGI :: Application
Classifier: Topic :: Software Development :: Libraries :: Application Frameworks
Classifier: Typing :: Typed
Requires-Dist: Django (>=2.0,<4.0)
Project-URL: Repository, https://edugit.org/AlekSIS/libs/django-split-input
